[
    {
        "name":"Team Totals",
        "war":"1.1",
        "w":"7",
        "l":"2",
        "w-l%":".778",
        "era":"3.38",
        "g":"9",
        "gs":"9",
        "gf":"9",
        "cg":"0",
        "sho":"0",
        "sv":"3",
        "ip":"80.0",
        "h":"66",
        "r":"32",
        "er":"30",
        "hr":"13",
        "bb":"38",
        "ibb":"2",
        "so":"103",
        "hbp":"3",
        "bk":"0",
        "wp":"6",
        "bf":"335",
        "era+":"121",
        "fip":"4.27",
        "whip":"1.300",
        "h9":"7.4",
        "hr9":"1.5",
        "bb9":"4.3",
        "so9":"11.6",
        "so\/bb":"2.71",
        "season":"2026"
    }
]